{
    "triplets": [
        {
            "subject": {
                "name": "Antoni Kamieński",
                "type": "osoba",
                "description": "działacz kulturalny na Wołyniu"
            },
            "predicate": {
                "name": "hasFather"
            },
            "object": {
                "name": "Stanisław Kamieński",
                "type": "osoba",
                "description": "burgrabia krzemieniecki"
            },
            "result": true
        },
        {
            "subject": {
                "name": "Antoni Kamieński",
                "type": "osoba",
                "description": "działacz kulturalny na Wołyniu"
            },
            "predicate": {
                "name": "hasMother"
            },
            "object": {
                "name": "Barbara z Kuczabskich",
                "type": "osoba",
                "description": null
            },
            "result": true
        },
        {
            "subject": {
                "name": "Antoni Kamieński",
                "type": "osoba",
                "description": "działacz kulturalny na Wołyniu"
            },
            "predicate": {
                "name": "hasWife"
            },
            "object": {
                "name": "Franciszka Czarnocka",
                "type": "osoba",
                "description": null
            },
            "result": true
        },
        {
            "subject": {
                "name": "Antoni Kamieński",
                "type": "osoba",
                "description": "działacz kulturalny na Wołyniu"
            },
            "predicate": {
                "name": "hasSon"
            },
            "object": {
                "name": "Stanisław Kamieński",
                "type": "osoba",
                "description": null
            },
            "result": false
        },
        {
            "subject": {
                "name": "Antoni Kamieński",
                "type": "osoba",
                "description": "działacz kulturalny na Wołyniu"
            },
            "predicate": {
                "name": "hasSon"
            },
            "object": {
                "name": "Juliusz Kamieński",
                "type": "osoba",
                "description": null
            },
            "result": true
        },
        {
            "subject": {
                "name": "Antoni Kamieński",
                "type": "osoba",
                "description": "działacz kulturalny na Wołyniu"
            },
            "predicate": {
                "name": "placeOfBirth"
            },
            "object": {
                "name": "Ludwiszcze",
                "type": "miejscowość",
                "description": "miejscowość w powiecie krzemienieckim"
            },
            "result": true
        },
        {
            "subject": {
                "name": "Antoni Kamieński",
                "type": "osoba",
                "description": "działacz kulturalny na Wołyniu"
            },
            "predicate": {
                "name": "dateOfDeath"
            },
            "object": {
                "name": "1862-11-08",
                "type": "data",
                "description": null
            },
            "result": true
        },
        {
            "subject": {
                "name": "Antoni Kamieński",
                "type": "osoba",
                "description": "działacz kulturalny na Wołyniu"
            },
            "predicate": {
                "name": "nameOfSchoolOrUniversity"
            },
            "object": {
                "name": "Liceum Wołyńskie",
                "type": "uczelnia",
                "description": "szkoła w Krzemieńcu"
            },
            "result": true
        },
        {
            "subject": {
                "name": "Antoni Kamieński",
                "type": "osoba",
                "description": "działacz kulturalny na Wołyniu"
            },
            "predicate": {
                "name": "positionHeld"
            },
            "object": {
                "name": "podsędek sądu",
                "type": "urząd",
                "description": "w Starym Konstantynowie"
            },
            "result": true
        },
        {
            "subject": {
                "name": "Antoni Kamieński",
                "type": "osoba",
                "description": "działacz kulturalny na Wołyniu"
            },
            "predicate": {
                "name": "positionHeld"
            },
            "object": {
                "name": "kurator gimnazjum",
                "type": "urząd",
                "description": "w Równem"
            },
            "result": true
        },
        {
            "subject": {
                "name": "Antoni Kamieński",
                "type": "osoba",
                "description": "działacz kulturalny na Wołyniu"
            },
            "predicate": {
                "name": "hasAssets"
            },
            "object": {
                "name": "Kołki",
                "type": "miejscowość",
                "description": "wieś w powiecie starokonstantynowskim"
            },
            "result": true
        },
        {
            "subject": {
                "name": "Antoni Kamieński",
                "type": "osoba",
                "description": "działacz kulturalny na Wołyniu"
            },
            "predicate": {
                "name": "significantFigure"
            },
            "object": {
                "name": "Feliks Czacki",
                "type": "osoba",
                "description": "bratanek Tadeusza Czackiego"
            },
            "result": true
        },
        {
            "subject": {
                "name": "Antoni Kamieński",
                "type": "osoba",
                "description": "działacz kulturalny na Wołyniu"
            },
            "predicate": {
                "name": "significantFigure"
            },
            "object": {
                "name": "K. Kaczkowski",
                "type": "osoba",
                "description": null
            },
            "result": true
        },
        {
            "subject": {
                "name": "Antoni Kamieński",
                "type": "osoba",
                "description": "działacz kulturalny na Wołyniu"
            },
            "predicate": {
                "name": "significantFigure"
            },
            "object": {
                "name": "K. Sienkiewicz",
                "type": "osoba",
                "description": null
            },
            "result": true
        },
        {
            "subject": {
                "name": "Antoni Kamieński",
                "type": "osoba",
                "description": "działacz kulturalny na Wołyniu"
            },
            "predicate": {
                "name": "significantFigure"
            },
            "object": {
                "name": "A. Słowikowski",
                "type": "osoba",
                "description": null
            },
            "result": true
        },
        {
            "subject": {
                "name": "Antoni Kamieński",
                "type": "osoba",
                "description": "działacz kulturalny na Wołyniu"
            },
            "predicate": {
                "name": "significantFigure"
            },
            "object": {
                "name": "Tadeusz Czacki",
                "type": "osoba",
                "description": null
            },
            "result": true
        },
        {
            "subject": {
                "name": "Feliks Czacki",
                "type": "osoba",
                "description": "bratanek Tadeusza Czackiego"
            },
            "predicate": {
                "name": "hasUncle"
            },
            "object": {
                "name": "Tadeusz Czacki",
                "type": "osoba",
                "description": null
            },
            "result": false
        }
    ]
}